CapSolverpy/__init__.py
CapSolverpy/main.py
CapSolverpy-1.0.dist-info/METADATA
CapSolverpy-1.0.dist-info/WHEEL
CapSolverpy-1.0.dist-info/top_level.txt
CapSolverpy-1.0.dist-info/RECORD
