Metadata-Version: 2.1
Name: CapSolverpy
Version: 1.0
Summary: CapSolver.com library for Python
Home-page: https://github.com/neyboo/capsolverpy
Author: Neyboo Lux
Author-email: admin@archo.host
License: MIT
Project-URL: Documentation, https://github.com/neyboo/capsolverpy#readme
Project-URL: Source, https://github.com/neyboo/capsolverpy
Project-URL: Tracker, https://github.com/neyboo/capsolverpy/issues
Classifier: Development Status :: 4 - Beta
Classifier: License :: OSI Approved :: MIT License
Classifier: Programming Language :: Python :: 3
Classifier: Programming Language :: Python :: 3.6
Classifier: Programming Language :: Python :: 3.7
Classifier: Programming Language :: Python :: 3.8
Classifier: Programming Language :: Python :: 3.9
Requires: requests
Requires-Python: >=3
Requires-Dist: requests
Requires-Dist: six
